{"zh_guide_custom_configs.md":"J9WTL7xK","guide_getting-started.md":"ZGJ1UGTK","config_blind.md":"FwcPmUKb","guide_image.md":"_GAMA_JV","zh_guide_getting-started.md":"pRpu_xia","zh_guide_image.md":"3_kQYeuu","guide_blind-watermark.md":"gZXEybK-","zh_guide_what-is-this.md":"HzCIXanW","guide_what-is-this.md":"MS8Y9PBx","index.md":"9dzCtKhJ","zh_config_index.md":"ISDu3uxo","zh_config_blind.md":"A0sDiUgE","zh_config_blind-decode.md":"wDOZIl_-","zh_guide_blind-watermark.md":"F3Yu7oAA","zh_config_function.md":"7_ZRN5uc","zh_guide_watermark.md":"CNiyfbsE","config_index.md":"86FNKvfZ","guide_watermark.md":"FjafbF-b","guide_custom_configs.md":"n5pm49VO","config_blind-decode.md":"o9bo-opv","zh_index.md":"Etsyo2Uw","config_function.md":"51mWJC-7"}
