{"guide_getting-started.md":"g0XM0DNw","config_index.md":"SidR-Gpa","zh_guide_getting-started.md":"jOmAnHUk","index.md":"3yovo3ol","guide_what-is-this.md":"k7n23-6W","guide_image.md":"sZz45cKn","guide_custom_configs.md":"VMXrttYC","zh_config_function.md":"6CkWbwX5","guide_watermark.md":"v635hmuI","zh_config_index.md":"GDjcE70V","zh_guide_watermark.md":"X4cJjtzk","config_function.md":"SoPzcAzX","zh_guide_custom_configs.md":"1Jc_E_7d","config_blind.md":"yFtckr9p","zh_index.md":"ICcGYBnO","zh_guide_what-is-this.md":"g0Ogp8m6","zh_guide_blind-watermark.md":"MKNbABVN","zh_config_blind.md":"KSjx4CG_","guide_blind-watermark.md":"jw1uV_mE","zh_config_blind-decode.md":"gS4j8cy1","zh_guide_image.md":"CzPN6Nmz","config_blind-decode.md":"Ah3OsVXN"}
