{"guide_custom_configs.md":"15f283bc","guide_blind-watermark.md":"97e7510a","config_index.md":"dbac4379","config_blind.md":"f04e94e1","config_blind-decode.md":"3beec20f","zh_guide_custom_configs.md":"41942e59","index.md":"a6c13804","zh_config_blind-decode.md":"dbb74621","zh_config_function.md":"ea0593ec","zh_config_index.md":"daa436c1","zh_config_blind.md":"432d4163","zh_guide_blind-watermark.md":"70692f53","config_function.md":"c5181eca","zh_index.md":"1a813a3d","zh_guide_what-is-this.md":"b8ccfae7","zh_guide_watermark.md":"0896f8e3","zh_guide_getting-started.md":"a12305af","zh_guide_image.md":"88807339","guide_getting-started.md":"fb2eeb6e","guide_image.md":"391ee714","guide_watermark.md":"4a9b1360","guide_what-is-this.md":"cf8a9a86"}
